touchfish/__init__.py
touchfish/fish.py
touchfish/recipe_view.py
touchfish/touchfish.py
touchfish-1.1.1.dist-info/METADATA
touchfish-1.1.1.dist-info/WHEEL
touchfish-1.1.1.dist-info/top_level.txt
touchfish-1.1.1.dist-info/RECORD
