Metadata-Version: 2.1
Name: touchfish
Version: 1.1.1
Summary: python sdk for touchfish
Author: yzjsswk
Author-email: yzjsswk@gmail.com
Classifier: Programming Language :: Python :: 3
Classifier: License :: OSI Approved :: MIT License
Classifier: Operating System :: OS Independent
Requires-Python: >=3.11
Requires-Dist: yfunc
Requires-Dist: requests
Requires-Dist: httpx
Requires-Dist: sympy
Requires-Dist: matplotlib
Requires-Dist: beautifulsoup4
